django_client_logger/VERSION
django_client_logger/__init__.py
django_client_logger/logger.py
django_client_logger/tests.py
django_client_logger/urls.py
django_client_logger/views.py
django_client_logger/static/js/log4javascript.js
django_client_logger/static/js/log4javascript.js_min
django_client_logger/static/js/logger.js
django_client_logger/templates/logger.html
django_client_logger-3.1.1.dist-info/licenses/LICENSE
django_client_logger-3.1.1.dist-info/METADATA
django_client_logger-3.1.1.dist-info/WHEEL
django_client_logger-3.1.1.dist-info/top_level.txt
django_client_logger-3.1.1.dist-info/RECORD
