Metadata-Version: 2.4
Name: django_client_logger
Version: 3.1.1
Summary: Client logging application for django
Home-page: https://github.com/uw-it-aca/django_client_logger
Author: UW-IT SETS
Author-email: aca-it@uw.edu
License: Apache License, Version 2.0
Classifier: Intended Audience :: Developers
Classifier: License :: OSI Approved :: Apache Software License
Classifier: Operating System :: OS Independent
Classifier: Programming Language :: Python
License-File: LICENSE
Requires-Dist: Django
Requires-Dist: mock
Requires-Dist: django-userservice
Dynamic: author
Dynamic: author-email
Dynamic: classifier
Dynamic: description
Dynamic: home-page
Dynamic: license
Dynamic: license-file
Dynamic: requires-dist
Dynamic: summary
